libquery_extensions/__init__.py
libquery_extensions/alabama_maps/__init__.py
libquery_extensions/alabama_maps/_fetch_metadata.py
libquery_extensions/alabama_maps/_querier.py
libquery_extensions/alabama_maps/_typing.py
libquery_extensions/british_library/_utils/fetch_metadata.py
libquery_extensions/british_library/_utils/fetch_queries.py
libquery_extensions/british_library/collection_items/__init__.py
libquery_extensions/british_library/collection_items/_fetch_image.py
libquery_extensions/british_library/collection_items/_fetch_metadata.py
libquery_extensions/british_library/collection_items/_fetch_queries.py
libquery_extensions/british_library/collection_items/_querier.py
libquery_extensions/british_library/collection_items/_typing.py
libquery_extensions/british_library/collection_items/_utils.py
libquery_extensions/british_library/images_online/__init__.py
libquery_extensions/british_library/images_online/_fetch_image.py
libquery_extensions/british_library/images_online/_fetch_metadata.py
libquery_extensions/british_library/images_online/_fetch_queries.py
libquery_extensions/british_library/images_online/_querier.py
libquery_extensions/british_library/images_online/_typing.py
libquery_extensions/british_library/online_gallery/__init__.py
libquery_extensions/british_library/online_gallery/_fetch_image.py
libquery_extensions/british_library/online_gallery/_fetch_metadata.py
libquery_extensions/british_library/online_gallery/_fetch_queries.py
libquery_extensions/british_library/online_gallery/_querier.py
libquery_extensions/british_library/online_gallery/_typing.py
libquery_extensions/british_library/online_gallery/_utils.py
libquery_extensions/get_chrome_driver.py
libquery_extensions/telefact/__init__.py
libquery_extensions/telefact/_fetch_metadata.py
libquery_extensions/telefact/_querier.py
libquery_extensions/telefact/_typing.py
libquery_extensions-0.1.1.dist-info/LICENSE
libquery_extensions-0.1.1.dist-info/METADATA
libquery_extensions-0.1.1.dist-info/WHEEL
libquery_extensions-0.1.1.dist-info/RECORD
