Metadata-Version: 2.1
Name: libquery-extensions
Version: 0.1.1
Summary: 
Author: Yu Zhang
Author-email: yuzhang94@outlook.com
Requires-Python: >=3.10,<4.0
Classifier: Programming Language :: Python :: 3
Classifier: Programming Language :: Python :: 3.10
Classifier: Programming Language :: Python :: 3.11
Requires-Dist: backoff (>=2.2.1,<3.0.0)
Requires-Dist: cssutils (>=2.7.1,<3.0.0)
Requires-Dist: libquery (>=0.1.1,<0.2.0)
Requires-Dist: requests (>=2.31.0,<3.0.0)
Requires-Dist: selenium (>=4.10.0,<5.0.0)
Requires-Dist: tqdm (>=4.65.0,<5.0.0)
Requires-Dist: typing-extensions (>=4.7.1,<5.0.0)
Requires-Dist: webdriver-manager (>=3.8.6,<4.0.0)
